{
  "世界观构造师_玄幻世界构建技巧_2026": {
    "skill_name": "世界观构造师",
    "topic": "玄幻世界构建技巧",
    "year": 2026,
    "result": {
      "topic": "玄幻世界构建技巧",
      "skill_name": "世界观构造师",
      "learned_at": "2026-04-29T16:47:58.867396",
      "key_points": [],
      "trends": [],
      "tips": [],
      "search_results": [
        {
          "title": "网文写作核心技巧",
          "content": "1.节奏：每300字一个小冲突，每1000字一个高潮 2.情绪：爽点要集中，虐点要简短 3.人设：标签化、记忆点、差异化 4.对话：推动剧情、不水、可视化",
          "source": "写作技巧"
        },
        {
          "title": "网文写作核心技巧",
          "content": "1.节奏：每300字一个小冲突，每1000字一个高潮 2.情绪：爽点要集中，虐点要简短 3.人设：标签化、记忆点、差异化 4.对话：推动剧情、不水、可视化",
          "source": "写作技巧"
        }
      ]
    },
    "cache_time": "2026-04-29T16:47:58.868155",
    "queries": [
      "玄幻世界构建技巧",
      "2026 玄幻世界构建技巧"
    ]
  },
  "战斗设计师_战斗场景描写技巧_2026": {
    "skill_name": "战斗设计师",
    "topic": "战斗场景描写技巧",
    "year": 2026,
    "result": {
      "topic": "战斗场景描写技巧",
      "skill_name": "战斗设计师",
      "learned_at": "2026-04-29T16:47:58.869098",
      "key_points": [],
      "trends": [],
      "tips": [],
      "search_results": [
        {
          "title": "网文写作核心技巧",
          "content": "1.节奏：每300字一个小冲突，每1000字一个高潮 2.情绪：爽点要集中，虐点要简短 3.人设：标签化、记忆点、差异化 4.对话：推动剧情、不水、可视化",
          "source": "写作技巧"
        },
        {
          "title": "网文写作核心技巧",
          "content": "1.节奏：每300字一个小冲突，每1000字一个高潮 2.情绪：爽点要集中，虐点要简短 3.人设：标签化、记忆点、差异化 4.对话：推动剧情、不水、可视化",
          "source": "写作技巧"
        }
      ]
    },
    "cache_time": "2026-04-29T16:47:58.869157",
    "queries": [
      "战斗场景描写技巧",
      "2026 战斗场景描写技巧"
    ]
  },
  "场景构造师_环境氛围营造_2026": {
    "skill_name": "场景构造师",
    "topic": "环境氛围营造",
    "year": 2026,
    "result": {
      "topic": "环境氛围营造",
      "skill_name": "场景构造师",
      "learned_at": "2026-04-29T16:47:58.870248",
      "key_points": [],
      "trends": [],
      "tips": [],
      "search_results": []
    },
    "cache_time": "2026-04-29T16:47:58.870266",
    "queries": [
      "环境氛围营造",
      "2026 环境氛围营造"
    ]
  },
  "对话设计师_对话个性塑造_2026": {
    "skill_name": "对话设计师",
    "topic": "对话个性塑造",
    "year": 2026,
    "result": {
      "topic": "对话个性塑造",
      "skill_name": "对话设计师",
      "learned_at": "2026-04-29T16:47:58.870706",
      "key_points": [],
      "trends": [],
      "tips": [],
      "search_results": []
    },
    "cache_time": "2026-04-29T16:47:58.870725",
    "queries": [
      "对话个性塑造",
      "2026 对话个性塑造"
    ]
  },
  "去AI痕迹监督官_AI痕迹识别技巧_2026": {
    "skill_name": "去AI痕迹监督官",
    "topic": "AI痕迹识别技巧",
    "year": 2026,
    "result": {
      "topic": "AI痕迹识别技巧",
      "skill_name": "去AI痕迹监督官",
      "learned_at": "2026-04-29T16:47:58.872335",
      "key_points": [],
      "trends": [],
      "tips": [],
      "search_results": [
        {
          "title": "网文写作核心技巧",
          "content": "1.节奏：每300字一个小冲突，每1000字一个高潮 2.情绪：爽点要集中，虐点要简短 3.人设：标签化、记忆点、差异化 4.对话：推动剧情、不水、可视化",
          "source": "写作技巧"
        },
        {
          "title": "网文写作核心技巧",
          "content": "1.节奏：每300字一个小冲突，每1000字一个高潮 2.情绪：爽点要集中，虐点要简短 3.人设：标签化、记忆点、差异化 4.对话：推动剧情、不水、可视化",
          "source": "写作技巧"
        }
      ]
    },
    "cache_time": "2026-04-29T16:47:58.872389",
    "queries": [
      "AI痕迹识别技巧",
      "2026 AI痕迹识别技巧"
    ]
  },
  "质量审计师_小说质量评估标准_2026": {
    "skill_name": "质量审计师",
    "topic": "小说质量评估标准",
    "year": 2026,
    "result": {
      "topic": "小说质量评估标准",
      "skill_name": "质量审计师",
      "learned_at": "2026-04-29T16:47:58.873369",
      "key_points": [],
      "trends": [],
      "tips": [],
      "search_results": []
    },
    "cache_time": "2026-04-29T16:47:58.873385",
    "queries": [
      "小说质量评估标准",
      "2026 小说质量评估标准"
    ]
  },
  "学习大师_网络小说趋势分析_2026": {
    "skill_name": "学习大师",
    "topic": "网络小说趋势分析",
    "year": 2026,
    "result": {
      "topic": "网络小说趋势分析",
      "skill_name": "学习大师",
      "learned_at": "2026-04-29T16:47:58.873873",
      "key_points": [],
      "trends": [],
      "tips": [],
      "search_results": []
    },
    "cache_time": "2026-04-29T16:47:58.873888",
    "queries": [
      "网络小说趋势分析",
      "2026 网络小说趋势分析"
    ]
  },
  "规则掌控者_自然规则设定_2026": {
    "skill_name": "规则掌控者",
    "topic": "自然规则设定",
    "year": 2026,
    "result": {
      "topic": "自然规则设定",
      "skill_name": "规则掌控者",
      "learned_at": "2026-04-29T16:47:58.874962",
      "key_points": [],
      "trends": [],
      "tips": [],
      "search_results": []
    },
    "cache_time": "2026-04-29T16:47:58.874979",
    "queries": [
      "自然规则设定",
      "2026 自然规则设定"
    ]
  },
  "词汇大师_词汇收集与整理_2026": {
    "skill_name": "词汇大师",
    "topic": "词汇收集与整理",
    "year": 2026,
    "result": {
      "topic": "词汇收集与整理",
      "skill_name": "词汇大师",
      "learned_at": "2026-04-29T16:47:58.875458",
      "key_points": [],
      "trends": [],
      "tips": [],
      "search_results": []
    },
    "cache_time": "2026-04-29T16:47:58.875483",
    "queries": [
      "词汇收集与整理",
      "2026 词汇收集与整理"
    ]
  },
  "剧情构造师_三幕式结构设计_2026": {
    "skill_name": "剧情构造师",
    "topic": "三幕式结构设计",
    "year": 2026,
    "result": {
      "topic": "三幕式结构设计",
      "skill_name": "剧情构造师",
      "learned_at": "2026-04-29T16:48:00.370704",
      "key_points": [],
      "trends": [],
      "tips": [],
      "search_results": []
    },
    "cache_time": "2026-04-29T16:48:00.370737",
    "queries": [
      "三幕式结构 英雄之旅 故事框架",
      "悬疑小说 反转设计 伏笔回收",
      "网络小说 剧情节奏 高潮安排",
      "故事结构 起承转合 章节设计",
      "三幕式结构设计"
    ]
  },
  "角色塑造师_角色性格刻画方法_2026": {
    "skill_name": "角色塑造师",
    "topic": "角色性格刻画方法",
    "year": 2026,
    "result": {
      "topic": "角色性格刻画方法",
      "skill_name": "角色塑造师",
      "learned_at": "2026-04-29T17:22:53.098776",
      "key_points": [],
      "trends": [],
      "tips": [],
      "search_results": []
    },
    "cache_time": "2026-04-29T17:22:53.098805",
    "queries": [
      "小说人物塑造 性格刻画 方法",
      "反派角色设计 动机背景",
      "主角成长弧光 变化过程",
      "人物关系 矛盾冲突 情感线",
      "角色性格刻画方法"
    ]
  },
  "去AI痕迹监督官_自然语言优化_2026": {
    "skill_name": "去AI痕迹监督官",
    "topic": "自然语言优化",
    "year": 2026,
    "result": {
      "topic": "自然语言优化",
      "skill_name": "去AI痕迹监督官",
      "learned_at": "2026-04-29T17:52:52.415462",
      "key_points": [],
      "trends": [],
      "tips": [],
      "search_results": []
    },
    "cache_time": "2026-04-29T17:52:52.415495",
    "queries": [
      "自然语言优化",
      "2026 自然语言优化"
    ]
  },
  "对话设计师_潜台词设计_2026": {
    "skill_name": "对话设计师",
    "topic": "潜台词设计",
    "year": 2026,
    "result": {
      "topic": "潜台词设计",
      "skill_name": "对话设计师",
      "learned_at": "2026-04-29T17:52:52.424499",
      "key_points": [],
      "trends": [],
      "tips": [],
      "search_results": []
    },
    "cache_time": "2026-04-29T17:52:52.424528",
    "queries": [
      "潜台词设计",
      "2026 潜台词设计"
    ]
  },
  "学习大师_经典文学研究_2026": {
    "skill_name": "学习大师",
    "topic": "经典文学研究",
    "year": 2026,
    "result": {
      "topic": "经典文学研究",
      "skill_name": "学习大师",
      "learned_at": "2026-04-29T17:52:52.442621",
      "key_points": [],
      "trends": [],
      "tips": [],
      "search_results": []
    },
    "cache_time": "2026-04-29T17:52:52.442649",
    "queries": [
      "经典文学研究",
      "2026 经典文学研究"
    ]
  },
  "规则掌控者_社会规则构建_2026": {
    "skill_name": "规则掌控者",
    "topic": "社会规则构建",
    "year": 2026,
    "result": {
      "topic": "社会规则构建",
      "skill_name": "规则掌控者",
      "learned_at": "2026-04-29T17:52:52.498973",
      "key_points": [],
      "trends": [],
      "tips": [],
      "search_results": []
    },
    "cache_time": "2026-04-29T17:52:52.499002",
    "queries": [
      "社会规则构建",
      "2026 社会规则构建"
    ]
  },
  "质量审计师_结构完整性检查_2026": {
    "skill_name": "质量审计师",
    "topic": "结构完整性检查",
    "year": 2026,
    "result": {
      "topic": "结构完整性检查",
      "skill_name": "质量审计师",
      "learned_at": "2026-04-29T17:52:52.500643",
      "key_points": [],
      "trends": [],
      "tips": [],
      "search_results": []
    },
    "cache_time": "2026-04-29T17:52:52.500661",
    "queries": [
      "结构完整性检查",
      "2026 结构完整性检查"
    ]
  },
  "世界观构造师_都市异能设定方法_2026": {
    "skill_name": "世界观构造师",
    "topic": "都市异能设定方法",
    "year": 2026,
    "result": {
      "topic": "都市异能设定方法",
      "skill_name": "世界观构造师",
      "learned_at": "2026-04-29T17:52:52.500827",
      "key_points": [],
      "trends": [],
      "tips": [],
      "search_results": []
    },
    "cache_time": "2026-04-29T17:52:52.500844",
    "queries": [
      "都市异能设定方法",
      "2026 都市异能设定方法"
    ]
  },
  "词汇大师_描写素材积累_2026": {
    "skill_name": "词汇大师",
    "topic": "描写素材积累",
    "year": 2026,
    "result": {
      "topic": "描写素材积累",
      "skill_name": "词汇大师",
      "learned_at": "2026-04-29T17:52:52.507521",
      "key_points": [],
      "trends": [],
      "tips": [],
      "search_results": []
    },
    "cache_time": "2026-04-29T17:52:52.507547",
    "queries": [
      "描写素材积累",
      "2026 描写素材积累"
    ]
  },
  "场景构造师_感官细节描写_2026": {
    "skill_name": "场景构造师",
    "topic": "感官细节描写",
    "year": 2026,
    "result": {
      "topic": "感官细节描写",
      "skill_name": "场景构造师",
      "learned_at": "2026-04-29T17:52:52.687971",
      "key_points": [],
      "trends": [],
      "tips": [],
      "search_results": []
    },
    "cache_time": "2026-04-29T17:52:52.688001",
    "queries": [
      "感官细节描写",
      "2026 感官细节描写"
    ]
  },
  "战斗设计师_招式命名艺术_2026": {
    "skill_name": "战斗设计师",
    "topic": "招式命名艺术",
    "year": 2026,
    "result": {
      "topic": "招式命名艺术",
      "skill_name": "战斗设计师",
      "learned_at": "2026-04-29T17:52:52.745140",
      "key_points": [],
      "trends": [],
      "tips": [],
      "search_results": []
    },
    "cache_time": "2026-04-29T17:52:52.745157",
    "queries": [
      "招式命名艺术",
      "2026 招式命名艺术"
    ]
  },
  "短篇小说爽文大师_2025 2026 短篇小说爽文类型 爆款_2026": {
    "skill_name": "短篇小说爽文大师",
    "topic": "2025 2026 短篇小说爽文类型 爆款",
    "year": 2026,
    "result": {
      "topic": "2025 2026 短篇小说爽文类型 爆款",
      "skill_name": "短篇小说爽文大师",
      "learned_at": "2026-04-29T18:12:26.959265",
      "key_points": [
        "23%",
        "42%",
        "19%",
        "45%",
        "16%",
        "37%",
        "14%",
        "38%",
        "根据番茄小说数据，2026年最火的短篇类型包括：恶毒女配逆袭（占比23%，同比增长42%）、重生年代文（19%，增长45%）、穿书系统文（16%，增长37%）、玄学悬疑（14%，增长38%）",
        "都市脑洞文崛起，遗物整理师、法医读心等冷门职业设定成为新风口"
      ],
      "trends": [
        "增长",
        "崛起",
        "火爆",
        "式微"
      ],
      "tips": [
        "黄金开篇公式：100字强钩子+300字冲突+500字反转+800字小高潮"
      ],
      "search_results": [
        {
          "title": "2026年短篇小说爆款类型分析",
          "content": "根据番茄小说数据，2026年最火的短篇类型包括：恶毒女配逆袭（占比23%，同比增长42%）、重生年代文（19%，增长45%）、穿书系统文（16%，增长37%）、玄学悬疑（14%，增长38%）。",
          "source": "行业报告"
        },
        {
          "title": "男频爆款题材分析",
          "content": "都市脑洞文崛起，遗物整理师、法医读心等冷门职业设定成为新风口。战神赘婿文持续火爆，但需要加入反套路元素。传统玄幻式微，种田流、稳健流兴起。",
          "source": "行业分析"
        },
        {
          "title": "女频热门题材趋势",
          "content": "恶毒女配洗白成顶流，主角不憋屈直接反杀更受欢迎。重生逆袭+空间囤货组合热度高。豪门甜宠要求马甲多、身份反差大。追妻火葬场依然有效，但需要女主有事业线。",
          "source": "平台分析"
        },
        {
          "title": "爆款开篇公式",
          "content": "黄金开篇公式：100字强钩子+300字冲突+500字反转+800字小高潮。开篇即冲突，拒绝铺设定。主角困境要具体（被退婚、被陷害、被嘲笑），金手指要早出。",
          "source": "写作教程"
        }
      ]
    },
    "cache_time": "2026-04-29T18:12:26.960039",
    "queries": [
      "2026年 短篇小说 爆款类型 热门题材",
      "2026年 短剧改编 热门网络小说",
      "男频 都市 玄幻 战神赘婿 爆款套路",
      "女频 重生 复仇 穿书 霸总 热门题材",
      "网络小说 开头写法 黄金三章 技巧"
    ]
  },
  "写作技巧大师_风格定位与统一_2026": {
    "skill_name": "写作技巧大师",
    "topic": "风格定位与统一",
    "year": 2026,
    "result": {
      "topic": "风格定位与统一",
      "skill_name": "写作技巧大师",
      "learned_at": "2026-04-29T18:12:27.297111",
      "key_points": [
        "1.节奏：每300字一个小冲突，每1000字一个高潮 2.情绪：爽点要集中，虐点要简短 3.人设：标签化、记忆点、差异化 4.对话：推动剧情、不水、可视化"
      ],
      "trends": [],
      "tips": [],
      "search_results": [
        {
          "title": "网文写作核心技巧",
          "content": "1.节奏：每300字一个小冲突，每1000字一个高潮 2.情绪：爽点要集中，虐点要简短 3.人设：标签化、记忆点、差异化 4.对话：推动剧情、不水、可视化",
          "source": "写作技巧"
        },
        {
          "title": "网文写作核心技巧",
          "content": "1.节奏：每300字一个小冲突，每1000字一个高潮 2.情绪：爽点要集中，虐点要简短 3.人设：标签化、记忆点、差异化 4.对话：推动剧情、不水、可视化",
          "source": "写作技巧"
        },
        {
          "title": "网文写作核心技巧",
          "content": "1.节奏：每300字一个小冲突，每1000字一个高潮 2.情绪：爽点要集中，虐点要简短 3.人设：标签化、记忆点、差异化 4.对话：推动剧情、不水、可视化",
          "source": "写作技巧"
        }
      ]
    },
    "cache_time": "2026-04-29T18:12:27.297203",
    "queries": [
      "小说写作技巧 情节设计 冲突制造",
      "人物塑造 角色弧光 性格刻画",
      "网络文学 商业化写作 技巧",
      "小说开头 钩子设计 悬念营造",
      "对话写作 潜台词 情感表达"
    ]
  },
  "角色塑造师_人物动机设定_2026": {
    "skill_name": "角色塑造师",
    "topic": "人物动机设定",
    "year": 2026,
    "result": {
      "topic": "人物动机设定",
      "skill_name": "角色塑造师",
      "learned_at": "2026-04-29T18:42:28.230915",
      "key_points": [
        "世界观构造五要素：1.地理环境：地图、气候、资源分布 2.社会结构：阶级、权力体系、文化习俗 3.历史背景：时间线、重大事件、传说起源 4.规则设定：魔法/科技体系、力量等级 5.价值观：善恶标准、信仰体系"
      ],
      "trends": [],
      "tips": [],
      "search_results": [
        {
          "title": "小说世界观构造指南",
          "content": "世界观构造五要素：1.地理环境：地图、气候、资源分布 2.社会结构：阶级、权力体系、文化习俗 3.历史背景：时间线、重大事件、传说起源 4.规则设定：魔法/科技体系、力量等级 5.价值观：善恶标准、信仰体系。",
          "source": "写作指南"
        }
      ]
    },
    "cache_time": "2026-04-29T18:42:28.230991",
    "queries": [
      "小说人物塑造 性格刻画 方法",
      "反派角色设计 动机背景",
      "主角成长弧光 变化过程",
      "人物关系 矛盾冲突 情感线",
      "人物动机设定"
    ]
  },
  "剧情构造师_英雄之旅模板应用_2026": {
    "skill_name": "剧情构造师",
    "topic": "英雄之旅模板应用",
    "year": 2026,
    "result": {
      "topic": "英雄之旅模板应用",
      "skill_name": "剧情构造师",
      "learned_at": "2026-04-29T18:42:28.417218",
      "key_points": [
        "神转折三要素：1.铺垫要隐蔽：提前3-5章埋下线索 2.逻辑要自洽：反转后能合理解释前文 3.冲击要够强：打破读者预期",
        "经典反转模式：身份反转（仇人变亲人）、因果反转（好心办坏事）、时间反转（穿越/重生）、真假反转（梦境/幻觉）"
      ],
      "trends": [],
      "tips": [],
      "search_results": [
        {
          "title": "小说大反转剧情设计技巧",
          "content": "神转折三要素：1.铺垫要隐蔽：提前3-5章埋下线索 2.逻辑要自洽：反转后能合理解释前文 3.冲击要够强：打破读者预期。经典反转模式：身份反转（仇人变亲人）、因果反转（好心办坏事）、时间反转（穿越/重生）、真假反转（梦境/幻觉）。",
          "source": "写作教程"
        }
      ]
    },
    "cache_time": "2026-04-29T18:42:28.417335",
    "queries": [
      "三幕式结构 英雄之旅 故事框架",
      "悬疑小说 反转设计 伏笔回收",
      "网络小说 剧情节奏 高潮安排",
      "故事结构 起承转合 章节设计",
      "英雄之旅模板应用"
    ]
  },
  "短篇小说爽文大师_2025 2026 短剧改编热门题材_2026": {
    "skill_name": "短篇小说爽文大师",
    "topic": "2025 2026 短剧改编热门题材",
    "year": 2026,
    "result": {
      "topic": "2025 2026 短剧改编热门题材",
      "skill_name": "短篇小说爽文大师",
      "learned_at": "2026-04-29T18:42:30.373879",
      "key_points": [
        "23%",
        "42%",
        "19%",
        "45%",
        "16%",
        "37%",
        "14%",
        "38%",
        "根据番茄小说数据，2026年最火的短篇类型包括：恶毒女配逆袭（占比23%，同比增长42%）、重生年代文（19%，增长45%）、穿书系统文（16%，增长37%）、玄学悬疑（14%，增长38%）",
        "都市脑洞文崛起，遗物整理师、法医读心等冷门职业设定成为新风口"
      ],
      "trends": [
        "增长",
        "崛起",
        "火爆",
        "式微"
      ],
      "tips": [
        "黄金开篇公式：100字强钩子+300字冲突+500字反转+800字小高潮"
      ],
      "search_results": [
        {
          "title": "2026年短篇小说爆款类型分析",
          "content": "根据番茄小说数据，2026年最火的短篇类型包括：恶毒女配逆袭（占比23%，同比增长42%）、重生年代文（19%，增长45%）、穿书系统文（16%，增长37%）、玄学悬疑（14%，增长38%）。",
          "source": "行业报告"
        },
        {
          "title": "男频爆款题材分析",
          "content": "都市脑洞文崛起，遗物整理师、法医读心等冷门职业设定成为新风口。战神赘婿文持续火爆，但需要加入反套路元素。传统玄幻式微，种田流、稳健流兴起。",
          "source": "行业分析"
        },
        {
          "title": "女频热门题材趋势",
          "content": "恶毒女配洗白成顶流，主角不憋屈直接反杀更受欢迎。重生逆袭+空间囤货组合热度高。豪门甜宠要求马甲多、身份反差大。追妻火葬场依然有效，但需要女主有事业线。",
          "source": "平台分析"
        },
        {
          "title": "爆款开篇公式",
          "content": "黄金开篇公式：100字强钩子+300字冲突+500字反转+800字小高潮。开篇即冲突，拒绝铺设定。主角困境要具体（被退婚、被陷害、被嘲笑），金手指要早出。",
          "source": "写作教程"
        }
      ]
    },
    "cache_time": "2026-04-29T18:42:30.374174",
    "queries": [
      "2026年 短篇小说 爆款类型 热门题材",
      "2026年 短剧改编 热门网络小说",
      "男频 都市 玄幻 战神赘婿 爆款套路",
      "女频 重生 复仇 穿书 霸总 热门题材",
      "网络小说 开头写法 黄金三章 技巧"
    ]
  },
  "写作技巧大师_修辞手法运用_2026": {
    "skill_name": "写作技巧大师",
    "topic": "修辞手法运用",
    "year": 2026,
    "result": {
      "topic": "修辞手法运用",
      "skill_name": "写作技巧大师",
      "learned_at": "2026-04-29T18:42:30.692723",
      "key_points": [
        "1.节奏：每300字一个小冲突，每1000字一个高潮 2.情绪：爽点要集中，虐点要简短 3.人设：标签化、记忆点、差异化 4.对话：推动剧情、不水、可视化"
      ],
      "trends": [],
      "tips": [],
      "search_results": [
        {
          "title": "网文写作核心技巧",
          "content": "1.节奏：每300字一个小冲突，每1000字一个高潮 2.情绪：爽点要集中，虐点要简短 3.人设：标签化、记忆点、差异化 4.对话：推动剧情、不水、可视化",
          "source": "写作技巧"
        },
        {
          "title": "网文写作核心技巧",
          "content": "1.节奏：每300字一个小冲突，每1000字一个高潮 2.情绪：爽点要集中，虐点要简短 3.人设：标签化、记忆点、差异化 4.对话：推动剧情、不水、可视化",
          "source": "写作技巧"
        },
        {
          "title": "网文写作核心技巧",
          "content": "1.节奏：每300字一个小冲突，每1000字一个高潮 2.情绪：爽点要集中，虐点要简短 3.人设：标签化、记忆点、差异化 4.对话：推动剧情、不水、可视化",
          "source": "写作技巧"
        }
      ]
    },
    "cache_time": "2026-04-29T18:42:30.692846",
    "queries": [
      "小说写作技巧 情节设计 冲突制造",
      "人物塑造 角色弧光 性格刻画",
      "网络文学 商业化写作 技巧",
      "小说开头 钩子设计 悬念营造",
      "对话写作 潜台词 情感表达"
    ]
  },
  "世界观构造师_科幻世界规则设计_2026": {
    "skill_name": "世界观构造师",
    "topic": "科幻世界规则设计",
    "year": 2026,
    "result": {
      "topic": "科幻世界规则设计",
      "skill_name": "世界观构造师",
      "learned_at": "2026-04-29T19:12:27.301685",
      "key_points": [],
      "trends": [],
      "tips": [],
      "search_results": []
    },
    "cache_time": "2026-04-29T19:12:27.301705",
    "queries": [
      "科幻世界规则设计",
      "2026 科幻世界规则设计"
    ]
  },
  "词汇大师_语言风格优化_2026": {
    "skill_name": "词汇大师",
    "topic": "语言风格优化",
    "year": 2026,
    "result": {
      "topic": "语言风格优化",
      "skill_name": "词汇大师",
      "learned_at": "2026-04-29T19:12:27.331402",
      "key_points": [],
      "trends": [],
      "tips": [],
      "search_results": []
    },
    "cache_time": "2026-04-29T19:12:27.331416",
    "queries": [
      "语言风格优化",
      "2026 语言风格优化"
    ]
  },
  "质量审计师_人物一致性检查_2026": {
    "skill_name": "质量审计师",
    "topic": "人物一致性检查",
    "year": 2026,
    "result": {
      "topic": "人物一致性检查",
      "skill_name": "质量审计师",
      "learned_at": "2026-04-29T19:12:27.341127",
      "key_points": [],
      "trends": [],
      "tips": [],
      "search_results": []
    },
    "cache_time": "2026-04-29T19:12:27.341140",
    "queries": [
      "人物一致性检查",
      "2026 人物一致性检查"
    ]
  },
  "战斗设计师_战斗节奏控制_2026": {
    "skill_name": "战斗设计师",
    "topic": "战斗节奏控制",
    "year": 2026,
    "result": {
      "topic": "战斗节奏控制",
      "skill_name": "战斗设计师",
      "learned_at": "2026-04-29T19:12:27.472917",
      "key_points": [],
      "trends": [],
      "tips": [],
      "search_results": []
    },
    "cache_time": "2026-04-29T19:12:27.472931",
    "queries": [
      "战斗节奏控制",
      "2026 战斗节奏控制"
    ]
  },
  "对话设计师_对话节奏控制_2026": {
    "skill_name": "对话设计师",
    "topic": "对话节奏控制",
    "year": 2026,
    "result": {
      "topic": "对话节奏控制",
      "skill_name": "对话设计师",
      "learned_at": "2026-04-29T19:12:27.584750",
      "key_points": [],
      "trends": [],
      "tips": [],
      "search_results": []
    },
    "cache_time": "2026-04-29T19:12:27.584777",
    "queries": [
      "对话节奏控制",
      "2026 对话节奏控制"
    ]
  },
  "场景构造师_空间布局设计_2026": {
    "skill_name": "场景构造师",
    "topic": "空间布局设计",
    "year": 2026,
    "result": {
      "topic": "空间布局设计",
      "skill_name": "场景构造师",
      "learned_at": "2026-04-29T19:12:27.663379",
      "key_points": [],
      "trends": [],
      "tips": [],
      "search_results": []
    },
    "cache_time": "2026-04-29T19:12:27.663395",
    "queries": [
      "空间布局设计",
      "2026 空间布局设计"
    ]
  },
  "去AI痕迹监督官_人类风格模拟_2026": {
    "skill_name": "去AI痕迹监督官",
    "topic": "人类风格模拟",
    "year": 2026,
    "result": {
      "topic": "人类风格模拟",
      "skill_name": "去AI痕迹监督官",
      "learned_at": "2026-04-29T19:12:27.728058",
      "key_points": [],
      "trends": [],
      "tips": [],
      "search_results": []
    },
    "cache_time": "2026-04-29T19:12:27.728072",
    "queries": [
      "人类风格模拟",
      "2026 人类风格模拟"
    ]
  },
  "学习大师_写作技巧创新_2026": {
    "skill_name": "学习大师",
    "topic": "写作技巧创新",
    "year": 2026,
    "result": {
      "topic": "写作技巧创新",
      "skill_name": "学习大师",
      "learned_at": "2026-04-29T19:12:27.728620",
      "key_points": [
        "1.节奏：每300字一个小冲突，每1000字一个高潮 2.情绪：爽点要集中，虐点要简短 3.人设：标签化、记忆点、差异化 4.对话：推动剧情、不水、可视化"
      ],
      "trends": [],
      "tips": [],
      "search_results": [
        {
          "title": "网文写作核心技巧",
          "content": "1.节奏：每300字一个小冲突，每1000字一个高潮 2.情绪：爽点要集中，虐点要简短 3.人设：标签化、记忆点、差异化 4.对话：推动剧情、不水、可视化",
          "source": "写作技巧"
        },
        {
          "title": "网文写作核心技巧",
          "content": "1.节奏：每300字一个小冲突，每1000字一个高潮 2.情绪：爽点要集中，虐点要简短 3.人设：标签化、记忆点、差异化 4.对话：推动剧情、不水、可视化",
          "source": "写作技巧"
        }
      ]
    },
    "cache_time": "2026-04-29T19:12:27.728693",
    "queries": [
      "写作技巧创新",
      "2026 写作技巧创新"
    ]
  },
  "规则掌控者_特殊规则设计_2026": {
    "skill_name": "规则掌控者",
    "topic": "特殊规则设计",
    "year": 2026,
    "result": {
      "topic": "特殊规则设计",
      "skill_name": "规则掌控者",
      "learned_at": "2026-04-29T19:12:27.735846",
      "key_points": [],
      "trends": [],
      "tips": [],
      "search_results": []
    },
    "cache_time": "2026-04-29T19:12:27.735861",
    "queries": [
      "特殊规则设计",
      "2026 特殊规则设计"
    ]
  },
  "角色塑造师_角色成长弧光设计_2026": {
    "skill_name": "角色塑造师",
    "topic": "角色成长弧光设计",
    "year": 2026,
    "result": {
      "topic": "角色成长弧光设计",
      "skill_name": "角色塑造师",
      "learned_at": "2026-04-29T19:12:31.573493",
      "key_points": [
        "世界观构造五要素：1.地理环境：地图、气候、资源分布 2.社会结构：阶级、权力体系、文化习俗 3.历史背景：时间线、重大事件、传说起源 4.规则设定：魔法/科技体系、力量等级 5.价值观：善恶标准、信仰体系"
      ],
      "trends": [],
      "tips": [],
      "search_results": [
        {
          "title": "小说世界观构造指南",
          "content": "世界观构造五要素：1.地理环境：地图、气候、资源分布 2.社会结构：阶级、权力体系、文化习俗 3.历史背景：时间线、重大事件、传说起源 4.规则设定：魔法/科技体系、力量等级 5.价值观：善恶标准、信仰体系。",
          "source": "写作指南"
        }
      ]
    },
    "cache_time": "2026-04-29T19:12:31.573598",
    "queries": [
      "小说人物塑造 性格刻画 方法",
      "反派角色设计 动机背景",
      "主角成长弧光 变化过程",
      "人物关系 矛盾冲突 情感线",
      "角色成长弧光设计"
    ]
  },
  "剧情构造师_悬疑反转设计技巧_2026": {
    "skill_name": "剧情构造师",
    "topic": "悬疑反转设计技巧",
    "year": 2026,
    "result": {
      "topic": "悬疑反转设计技巧",
      "skill_name": "剧情构造师",
      "learned_at": "2026-04-29T19:12:31.820967",
      "key_points": [
        "神转折三要素：1.铺垫要隐蔽：提前3-5章埋下线索 2.逻辑要自洽：反转后能合理解释前文 3.冲击要够强：打破读者预期",
        "经典反转模式：身份反转（仇人变亲人）、因果反转（好心办坏事）、时间反转（穿越/重生）、真假反转（梦境/幻觉）",
        "1.节奏：每300字一个小冲突，每1000字一个高潮 2.情绪：爽点要集中，虐点要简短 3.人设：标签化、记忆点、差异化 4.对话：推动剧情、不水、可视化"
      ],
      "trends": [],
      "tips": [],
      "search_results": [
        {
          "title": "小说大反转剧情设计技巧",
          "content": "神转折三要素：1.铺垫要隐蔽：提前3-5章埋下线索 2.逻辑要自洽：反转后能合理解释前文 3.冲击要够强：打破读者预期。经典反转模式：身份反转（仇人变亲人）、因果反转（好心办坏事）、时间反转（穿越/重生）、真假反转（梦境/幻觉）。",
          "source": "写作教程"
        },
        {
          "title": "网文写作核心技巧",
          "content": "1.节奏：每300字一个小冲突，每1000字一个高潮 2.情绪：爽点要集中，虐点要简短 3.人设：标签化、记忆点、差异化 4.对话：推动剧情、不水、可视化",
          "source": "写作技巧"
        }
      ]
    },
    "cache_time": "2026-04-29T19:12:31.821050",
    "queries": [
      "三幕式结构 英雄之旅 故事框架",
      "悬疑小说 反转设计 伏笔回收",
      "网络小说 剧情节奏 高潮安排",
      "故事结构 起承转合 章节设计",
      "悬疑反转设计技巧"
    ]
  },
  "短篇小说爽文大师_男频爽文最新趋势 套路创新_2026": {
    "skill_name": "短篇小说爽文大师",
    "topic": "男频爽文最新趋势 套路创新",
    "year": 2026,
    "result": {
      "topic": "男频爽文最新趋势 套路创新",
      "skill_name": "短篇小说爽文大师",
      "learned_at": "2026-04-29T19:12:33.700427",
      "key_points": [
        "23%",
        "42%",
        "19%",
        "45%",
        "16%",
        "37%",
        "14%",
        "38%",
        "根据番茄小说数据，2026年最火的短篇类型包括：恶毒女配逆袭（占比23%，同比增长42%）、重生年代文（19%，增长45%）、穿书系统文（16%，增长37%）、玄学悬疑（14%，增长38%）",
        "都市脑洞文崛起，遗物整理师、法医读心等冷门职业设定成为新风口"
      ],
      "trends": [
        "增长",
        "崛起",
        "火爆",
        "式微"
      ],
      "tips": [
        "黄金开篇公式：100字强钩子+300字冲突+500字反转+800字小高潮"
      ],
      "search_results": [
        {
          "title": "2026年短篇小说爆款类型分析",
          "content": "根据番茄小说数据，2026年最火的短篇类型包括：恶毒女配逆袭（占比23%，同比增长42%）、重生年代文（19%，增长45%）、穿书系统文（16%，增长37%）、玄学悬疑（14%，增长38%）。",
          "source": "行业报告"
        },
        {
          "title": "男频爆款题材分析",
          "content": "都市脑洞文崛起，遗物整理师、法医读心等冷门职业设定成为新风口。战神赘婿文持续火爆，但需要加入反套路元素。传统玄幻式微，种田流、稳健流兴起。",
          "source": "行业分析"
        },
        {
          "title": "女频热门题材趋势",
          "content": "恶毒女配洗白成顶流，主角不憋屈直接反杀更受欢迎。重生逆袭+空间囤货组合热度高。豪门甜宠要求马甲多、身份反差大。追妻火葬场依然有效，但需要女主有事业线。",
          "source": "平台分析"
        },
        {
          "title": "爆款开篇公式",
          "content": "黄金开篇公式：100字强钩子+300字冲突+500字反转+800字小高潮。开篇即冲突，拒绝铺设定。主角困境要具体（被退婚、被陷害、被嘲笑），金手指要早出。",
          "source": "写作教程"
        }
      ]
    },
    "cache_time": "2026-04-29T19:12:33.700620",
    "queries": [
      "2026年 短篇小说 爆款类型 热门题材",
      "2026年 短剧改编 热门网络小说",
      "男频 都市 玄幻 战神赘婿 爆款套路",
      "女频 重生 复仇 穿书 霸总 热门题材",
      "网络小说 开头写法 黄金三章 技巧"
    ]
  },
  "写作技巧大师_叙事视角选择_2026": {
    "skill_name": "写作技巧大师",
    "topic": "叙事视角选择",
    "year": 2026,
    "result": {
      "topic": "叙事视角选择",
      "skill_name": "写作技巧大师",
      "learned_at": "2026-04-29T19:12:34.162036",
      "key_points": [
        "1.节奏：每300字一个小冲突，每1000字一个高潮 2.情绪：爽点要集中，虐点要简短 3.人设：标签化、记忆点、差异化 4.对话：推动剧情、不水、可视化"
      ],
      "trends": [],
      "tips": [],
      "search_results": [
        {
          "title": "网文写作核心技巧",
          "content": "1.节奏：每300字一个小冲突，每1000字一个高潮 2.情绪：爽点要集中，虐点要简短 3.人设：标签化、记忆点、差异化 4.对话：推动剧情、不水、可视化",
          "source": "写作技巧"
        },
        {
          "title": "网文写作核心技巧",
          "content": "1.节奏：每300字一个小冲突，每1000字一个高潮 2.情绪：爽点要集中，虐点要简短 3.人设：标签化、记忆点、差异化 4.对话：推动剧情、不水、可视化",
          "source": "写作技巧"
        },
        {
          "title": "网文写作核心技巧",
          "content": "1.节奏：每300字一个小冲突，每1000字一个高潮 2.情绪：爽点要集中，虐点要简短 3.人设：标签化、记忆点、差异化 4.对话：推动剧情、不水、可视化",
          "source": "写作技巧"
        }
      ]
    },
    "cache_time": "2026-04-29T19:12:34.162223",
    "queries": [
      "小说写作技巧 情节设计 冲突制造",
      "人物塑造 角色弧光 性格刻画",
      "网络文学 商业化写作 技巧",
      "小说开头 钩子设计 悬念营造",
      "对话写作 潜台词 情感表达"
    ]
  },
  "世界观构造师_历史架空背景构建_2026": {
    "skill_name": "世界观构造师",
    "topic": "历史架空背景构建",
    "year": 2026,
    "result": {
      "topic": "历史架空背景构建",
      "skill_name": "世界观构造师",
      "learned_at": "2026-04-29T19:42:29.181400",
      "key_points": [
        "世界观构造五要素：1.地理环境：地图、气候、资源分布 2.社会结构：阶级、权力体系、文化习俗 3.历史背景：时间线、重大事件、传说起源 4.规则设定：魔法/科技体系、力量等级 5.价值观：善恶标准、信仰体系"
      ],
      "trends": [],
      "tips": [],
      "search_results": [
        {
          "title": "小说世界观构造指南",
          "content": "世界观构造五要素：1.地理环境：地图、气候、资源分布 2.社会结构：阶级、权力体系、文化习俗 3.历史背景：时间线、重大事件、传说起源 4.规则设定：魔法/科技体系、力量等级 5.价值观：善恶标准、信仰体系。",
          "source": "写作指南"
        },
        {
          "title": "小说世界观构造指南",
          "content": "世界观构造五要素：1.地理环境：地图、气候、资源分布 2.社会结构：阶级、权力体系、文化习俗 3.历史背景：时间线、重大事件、传说起源 4.规则设定：魔法/科技体系、力量等级 5.价值观：善恶标准、信仰体系。",
          "source": "写作指南"
        }
      ]
    },
    "cache_time": "2026-04-29T19:42:29.181493",
    "queries": [
      "历史架空背景构建",
      "2026 历史架空背景构建"
    ]
  },
  "质量审计师_逻辑合理性验证_2026": {
    "skill_name": "质量审计师",
    "topic": "逻辑合理性验证",
    "year": 2026,
    "result": {
      "topic": "逻辑合理性验证",
      "skill_name": "质量审计师",
      "learned_at": "2026-04-29T19:42:29.238136",
      "key_points": [],
      "trends": [],
      "tips": [],
      "search_results": []
    },
    "cache_time": "2026-04-29T19:42:29.238151",
    "queries": [
      "逻辑合理性验证",
      "2026 逻辑合理性验证"
    ]
  },
  "词汇大师_专业术语应用_2026": {
    "skill_name": "词汇大师",
    "topic": "专业术语应用",
    "year": 2026,
    "result": {
      "topic": "专业术语应用",
      "skill_name": "词汇大师",
      "learned_at": "2026-04-29T19:42:29.251336",
      "key_points": [],
      "trends": [],
      "tips": [],
      "search_results": []
    },
    "cache_time": "2026-04-29T19:42:29.251350",
    "queries": [
      "专业术语应用",
      "2026 专业术语应用"
    ]
  },
  "战斗设计师_不同境界战斗差异_2026": {
    "skill_name": "战斗设计师",
    "topic": "不同境界战斗差异",
    "year": 2026,
    "result": {
      "topic": "不同境界战斗差异",
      "skill_name": "战斗设计师",
      "learned_at": "2026-04-29T19:42:29.339376",
      "key_points": [],
      "trends": [],
      "tips": [],
      "search_results": []
    },
    "cache_time": "2026-04-29T19:42:29.339394",
    "queries": [
      "不同境界战斗差异",
      "2026 不同境界战斗差异"
    ]
  },
  "对话设计师_情感对话描写_2026": {
    "skill_name": "对话设计师",
    "topic": "情感对话描写",
    "year": 2026,
    "result": {
      "topic": "情感对话描写",
      "skill_name": "对话设计师",
      "learned_at": "2026-04-29T19:42:29.493012",
      "key_points": [],
      "trends": [],
      "tips": [],
      "search_results": []
    },
    "cache_time": "2026-04-29T19:42:29.493028",
    "queries": [
      "情感对话描写",
      "2026 情感对话描写"
    ]
  },
  "场景构造师_场景转换技巧_2026": {
    "skill_name": "场景构造师",
    "topic": "场景转换技巧",
    "year": 2026,
    "result": {
      "topic": "场景转换技巧",
      "skill_name": "场景构造师",
      "learned_at": "2026-04-29T19:42:29.528922",
      "key_points": [
        "1.节奏：每300字一个小冲突，每1000字一个高潮 2.情绪：爽点要集中，虐点要简短 3.人设：标签化、记忆点、差异化 4.对话：推动剧情、不水、可视化"
      ],
      "trends": [],
      "tips": [],
      "search_results": [
        {
          "title": "网文写作核心技巧",
          "content": "1.节奏：每300字一个小冲突，每1000字一个高潮 2.情绪：爽点要集中，虐点要简短 3.人设：标签化、记忆点、差异化 4.对话：推动剧情、不水、可视化",
          "source": "写作技巧"
        },
        {
          "title": "网文写作核心技巧",
          "content": "1.节奏：每300字一个小冲突，每1000字一个高潮 2.情绪：爽点要集中，虐点要简短 3.人设：标签化、记忆点、差异化 4.对话：推动剧情、不水、可视化",
          "source": "写作技巧"
        }
      ]
    },
    "cache_time": "2026-04-29T19:42:29.528992",
    "queries": [
      "场景转换技巧",
      "2026 场景转换技巧"
    ]
  },
  "学习大师_跨领域知识融合_2026": {
    "skill_name": "学习大师",
    "topic": "跨领域知识融合",
    "year": 2026,
    "result": {
      "topic": "跨领域知识融合",
      "skill_name": "学习大师",
      "learned_at": "2026-04-29T19:42:29.570874",
      "key_points": [],
      "trends": [],
      "tips": [],
      "search_results": []
    },
    "cache_time": "2026-04-29T19:42:29.570888",
    "queries": [
      "跨领域知识融合",
      "2026 跨领域知识融合"
    ]
  },
  "去AI痕迹监督官_文本质量评估_2026": {
    "skill_name": "去AI痕迹监督官",
    "topic": "文本质量评估",
    "year": 2026,
    "result": {
      "topic": "文本质量评估",
      "skill_name": "去AI痕迹监督官",
      "learned_at": "2026-04-29T19:42:29.589080",
      "key_points": [],
      "trends": [],
      "tips": [],
      "search_results": []
    },
    "cache_time": "2026-04-29T19:42:29.589094",
    "queries": [
      "文本质量评估",
      "2026 文本质量评估"
    ]
  },
  "规则掌控者_规则一致性维护_2026": {
    "skill_name": "规则掌控者",
    "topic": "规则一致性维护",
    "year": 2026,
    "result": {
      "topic": "规则一致性维护",
      "skill_name": "规则掌控者",
      "learned_at": "2026-04-29T19:42:29.633188",
      "key_points": [],
      "trends": [],
      "tips": [],
      "search_results": []
    },
    "cache_time": "2026-04-29T19:42:29.633201",
    "queries": [
      "规则一致性维护",
      "2026 规则一致性维护"
    ]
  },
  "角色塑造师_人物关系网络构建_2026": {
    "skill_name": "角色塑造师",
    "topic": "人物关系网络构建",
    "year": 2026,
    "result": {
      "topic": "人物关系网络构建",
      "skill_name": "角色塑造师",
      "learned_at": "2026-04-29T19:42:34.976839",
      "key_points": [
        "世界观构造五要素：1.地理环境：地图、气候、资源分布 2.社会结构：阶级、权力体系、文化习俗 3.历史背景：时间线、重大事件、传说起源 4.规则设定：魔法/科技体系、力量等级 5.价值观：善恶标准、信仰体系"
      ],
      "trends": [],
      "tips": [],
      "search_results": [
        {
          "title": "小说世界观构造指南",
          "content": "世界观构造五要素：1.地理环境：地图、气候、资源分布 2.社会结构：阶级、权力体系、文化习俗 3.历史背景：时间线、重大事件、传说起源 4.规则设定：魔法/科技体系、力量等级 5.价值观：善恶标准、信仰体系。",
          "source": "写作指南"
        }
      ]
    },
    "cache_time": "2026-04-29T19:42:34.976901",
    "queries": [
      "小说人物塑造 性格刻画 方法",
      "反派角色设计 动机背景",
      "主角成长弧光 变化过程",
      "人物关系 矛盾冲突 情感线",
      "人物关系网络构建"
    ]
  },
  "剧情构造师_伏笔埋设与回收_2026": {
    "skill_name": "剧情构造师",
    "topic": "伏笔埋设与回收",
    "year": 2026,
    "result": {
      "topic": "伏笔埋设与回收",
      "skill_name": "剧情构造师",
      "learned_at": "2026-04-29T19:42:35.119859",
      "key_points": [
        "神转折三要素：1.铺垫要隐蔽：提前3-5章埋下线索 2.逻辑要自洽：反转后能合理解释前文 3.冲击要够强：打破读者预期",
        "经典反转模式：身份反转（仇人变亲人）、因果反转（好心办坏事）、时间反转（穿越/重生）、真假反转（梦境/幻觉）"
      ],
      "trends": [],
      "tips": [],
      "search_results": [
        {
          "title": "小说大反转剧情设计技巧",
          "content": "神转折三要素：1.铺垫要隐蔽：提前3-5章埋下线索 2.逻辑要自洽：反转后能合理解释前文 3.冲击要够强：打破读者预期。经典反转模式：身份反转（仇人变亲人）、因果反转（好心办坏事）、时间反转（穿越/重生）、真假反转（梦境/幻觉）。",
          "source": "写作教程"
        }
      ]
    },
    "cache_time": "2026-04-29T19:42:35.119937",
    "queries": [
      "三幕式结构 英雄之旅 故事框架",
      "悬疑小说 反转设计 伏笔回收",
      "网络小说 剧情节奏 高潮安排",
      "故事结构 起承转合 章节设计",
      "伏笔埋设与回收"
    ]
  },
  "短篇小说爽文大师_女频爽文最新趋势 套路创新_2026": {
    "skill_name": "短篇小说爽文大师",
    "topic": "女频爽文最新趋势 套路创新",
    "year": 2026,
    "result": {
      "topic": "女频爽文最新趋势 套路创新",
      "skill_name": "短篇小说爽文大师",
      "learned_at": "2026-04-29T19:42:37.065720",
      "key_points": [
        "23%",
        "42%",
        "19%",
        "45%",
        "16%",
        "37%",
        "14%",
        "38%",
        "根据番茄小说数据，2026年最火的短篇类型包括：恶毒女配逆袭（占比23%，同比增长42%）、重生年代文（19%，增长45%）、穿书系统文（16%，增长37%）、玄学悬疑（14%，增长38%）",
        "都市脑洞文崛起，遗物整理师、法医读心等冷门职业设定成为新风口"
      ],
      "trends": [
        "增长",
        "崛起",
        "火爆",
        "式微"
      ],
      "tips": [
        "黄金开篇公式：100字强钩子+300字冲突+500字反转+800字小高潮"
      ],
      "search_results": [
        {
          "title": "2026年短篇小说爆款类型分析",
          "content": "根据番茄小说数据，2026年最火的短篇类型包括：恶毒女配逆袭（占比23%，同比增长42%）、重生年代文（19%，增长45%）、穿书系统文（16%，增长37%）、玄学悬疑（14%，增长38%）。",
          "source": "行业报告"
        },
        {
          "title": "男频爆款题材分析",
          "content": "都市脑洞文崛起，遗物整理师、法医读心等冷门职业设定成为新风口。战神赘婿文持续火爆，但需要加入反套路元素。传统玄幻式微，种田流、稳健流兴起。",
          "source": "行业分析"
        },
        {
          "title": "女频热门题材趋势",
          "content": "恶毒女配洗白成顶流，主角不憋屈直接反杀更受欢迎。重生逆袭+空间囤货组合热度高。豪门甜宠要求马甲多、身份反差大。追妻火葬场依然有效，但需要女主有事业线。",
          "source": "平台分析"
        },
        {
          "title": "爆款开篇公式",
          "content": "黄金开篇公式：100字强钩子+300字冲突+500字反转+800字小高潮。开篇即冲突，拒绝铺设定。主角困境要具体（被退婚、被陷害、被嘲笑），金手指要早出。",
          "source": "写作教程"
        }
      ]
    },
    "cache_time": "2026-04-29T19:42:37.065978",
    "queries": [
      "2026年 短篇小说 爆款类型 热门题材",
      "2026年 短剧改编 热门网络小说",
      "男频 都市 玄幻 战神赘婿 爆款套路",
      "女频 重生 复仇 穿书 霸总 热门题材",
      "网络小说 开头写法 黄金三章 技巧"
    ]
  },
  "写作技巧大师_节奏控制技巧_2026": {
    "skill_name": "写作技巧大师",
    "topic": "节奏控制技巧",
    "year": 2026,
    "result": {
      "topic": "节奏控制技巧",
      "skill_name": "写作技巧大师",
      "learned_at": "2026-04-29T19:42:37.472343",
      "key_points": [
        "1.节奏：每300字一个小冲突，每1000字一个高潮 2.情绪：爽点要集中，虐点要简短 3.人设：标签化、记忆点、差异化 4.对话：推动剧情、不水、可视化"
      ],
      "trends": [],
      "tips": [],
      "search_results": [
        {
          "title": "网文写作核心技巧",
          "content": "1.节奏：每300字一个小冲突，每1000字一个高潮 2.情绪：爽点要集中，虐点要简短 3.人设：标签化、记忆点、差异化 4.对话：推动剧情、不水、可视化",
          "source": "写作技巧"
        },
        {
          "title": "网文写作核心技巧",
          "content": "1.节奏：每300字一个小冲突，每1000字一个高潮 2.情绪：爽点要集中，虐点要简短 3.人设：标签化、记忆点、差异化 4.对话：推动剧情、不水、可视化",
          "source": "写作技巧"
        },
        {
          "title": "网文写作核心技巧",
          "content": "1.节奏：每300字一个小冲突，每1000字一个高潮 2.情绪：爽点要集中，虐点要简短 3.人设：标签化、记忆点、差异化 4.对话：推动剧情、不水、可视化",
          "source": "写作技巧"
        }
      ]
    },
    "cache_time": "2026-04-29T19:42:37.472433",
    "queries": [
      "小说写作技巧 情节设计 冲突制造",
      "人物塑造 角色弧光 性格刻画",
      "网络文学 商业化写作 技巧",
      "小说开头 钩子设计 悬念营造",
      "对话写作 潜台词 情感表达"
    ]
  },
  "世界观构造师_世界规则一致性维护_2026": {
    "skill_name": "世界观构造师",
    "topic": "世界规则一致性维护",
    "year": 2026,
    "result": {
      "topic": "世界规则一致性维护",
      "skill_name": "世界观构造师",
      "learned_at": "2026-04-29T20:12:31.114411",
      "key_points": [],
      "trends": [],
      "tips": [],
      "search_results": []
    },
    "cache_time": "2026-04-29T20:12:31.114426",
    "queries": [
      "世界规则一致性维护",
      "2026 世界规则一致性维护"
    ]
  },
  "质量审计师_读者体验优化_2026": {
    "skill_name": "质量审计师",
    "topic": "读者体验优化",
    "year": 2026,
    "result": {
      "topic": "读者体验优化",
      "skill_name": "质量审计师",
      "learned_at": "2026-04-29T20:12:31.170676",
      "key_points": [],
      "trends": [],
      "tips": [],
      "search_results": []
    },
    "cache_time": "2026-04-29T20:12:31.170712",
    "queries": [
      "读者体验优化",
      "2026 读者体验优化"
    ]
  },
  "战斗设计师_特殊能力对决设计_2026": {
    "skill_name": "战斗设计师",
    "topic": "特殊能力对决设计",
    "year": 2026,
    "result": {
      "topic": "特殊能力对决设计",
      "skill_name": "战斗设计师",
      "learned_at": "2026-04-29T20:12:31.244470",
      "key_points": [],
      "trends": [],
      "tips": [],
      "search_results": []
    },
    "cache_time": "2026-04-29T20:12:31.244500",
    "queries": [
      "特殊能力对决设计",
      "2026 特殊能力对决设计"
    ]
  },
  "词汇大师_修辞丰富度提升_2026": {
    "skill_name": "词汇大师",
    "topic": "修辞丰富度提升",
    "year": 2026,
    "result": {
      "topic": "修辞丰富度提升",
      "skill_name": "词汇大师",
      "learned_at": "2026-04-29T20:12:31.252089",
      "key_points": [],
      "trends": [],
      "tips": [],
      "search_results": []
    },
    "cache_time": "2026-04-29T20:12:31.252103",
    "queries": [
      "修辞丰富度提升",
      "2026 修辞丰富度提升"
    ]
  },
  "场景构造师_地域特色体现_2026": {
    "skill_name": "场景构造师",
    "topic": "地域特色体现",
    "year": 2026,
    "result": {
      "topic": "地域特色体现",
      "skill_name": "场景构造师",
      "learned_at": "2026-04-29T20:12:31.457356",
      "key_points": [],
      "trends": [],
      "tips": [],
      "search_results": []
    },
    "cache_time": "2026-04-29T20:12:31.457384",
    "queries": [
      "地域特色体现",
      "2026 地域特色体现"
    ]
  },
  "对话设计师_冲突对话设计_2026": {
    "skill_name": "对话设计师",
    "topic": "冲突对话设计",
    "year": 2026,
    "result": {
      "topic": "冲突对话设计",
      "skill_name": "对话设计师",
      "learned_at": "2026-04-29T20:12:31.458296",
      "key_points": [],
      "trends": [],
      "tips": [],
      "search_results": []
    },
    "cache_time": "2026-04-29T20:12:31.458312",
    "queries": [
      "冲突对话设计",
      "2026 冲突对话设计"
    ]
  },
  "去AI痕迹监督官_写作风格多样性_2026": {
    "skill_name": "去AI痕迹监督官",
    "topic": "写作风格多样性",
    "year": 2026,
    "result": {
      "topic": "写作风格多样性",
      "skill_name": "去AI痕迹监督官",
      "learned_at": "2026-04-29T20:12:31.489766",
      "key_points": [
        "1.节奏：每300字一个小冲突，每1000字一个高潮 2.情绪：爽点要集中，虐点要简短 3.人设：标签化、记忆点、差异化 4.对话：推动剧情、不水、可视化"
      ],
      "trends": [],
      "tips": [],
      "search_results": [
        {
          "title": "网文写作核心技巧",
          "content": "1.节奏：每300字一个小冲突，每1000字一个高潮 2.情绪：爽点要集中，虐点要简短 3.人设：标签化、记忆点、差异化 4.对话：推动剧情、不水、可视化",
          "source": "写作技巧"
        },
        {
          "title": "网文写作核心技巧",
          "content": "1.节奏：每300字一个小冲突，每1000字一个高潮 2.情绪：爽点要集中，虐点要简短 3.人设：标签化、记忆点、差异化 4.对话：推动剧情、不水、可视化",
          "source": "写作技巧"
        }
      ]
    },
    "cache_time": "2026-04-29T20:12:31.489832",
    "queries": [
      "写作风格多样性",
      "2026 写作风格多样性"
    ]
  },
  "学习大师_学习方法优化_2026": {
    "skill_name": "学习大师",
    "topic": "学习方法优化",
    "year": 2026,
    "result": {
      "topic": "学习方法优化",
      "skill_name": "学习大师",
      "learned_at": "2026-04-29T20:12:31.490752",
      "key_points": [],
      "trends": [],
      "tips": [],
      "search_results": []
    },
    "cache_time": "2026-04-29T20:12:31.490771",
    "queries": [
      "学习方法优化",
      "2026 学习方法优化"
    ]
  }
}